nonebot_plugin_flomic/__init__.py
nonebot_plugin_flomic/Client.py
nonebot_plugin_flomic/Config.py
nonebot_plugin_flomic/Database.py
nonebot_plugin_flomic/Downloader.py
nonebot_plugin_flomic/Filter.py
nonebot_plugin_flomic/GroupFileManager.py
nonebot_plugin_flomic/MainManager.py
nonebot_plugin_flomic/utils.py
nonebot_plugin_flomic-0.2.0.dist-info/LICENSE
nonebot_plugin_flomic-0.2.0.dist-info/METADATA
nonebot_plugin_flomic-0.2.0.dist-info/WHEEL
nonebot_plugin_flomic-0.2.0.dist-info/RECORD
