Metadata-Version: 2.1
Name: nonebot-plugin-flomic
Version: 0.2.0
Summary: Nonebot plugin for using jmcomic crawler with multiple functions.
License: MIT
Author: florenz
Author-email: florenz@tju.edu.cn
Requires-Python: >=3.9,<4.0
Classifier: License :: OSI Approved :: MIT License
Classifier: Programming Language :: Python :: 3
Classifier: Programming Language :: Python :: 3.9
Classifier: Programming Language :: Python :: 3.10
Classifier: Programming Language :: Python :: 3.11
Classifier: Programming Language :: Python :: 3.12
Classifier: Programming Language :: Python :: 3.13
Requires-Dist: img2pdf (>=0.6.1)
Requires-Dist: jmcomic (>=2.6.0)
Requires-Dist: nonebot-adapter-onebot (>=2.4.6)
Requires-Dist: nonebot-plugin-alconna (>=0.58.4)
Requires-Dist: nonebot-plugin-localstore (>=0.7.4)
Requires-Dist: nonebot-plugin-uninfo (>=0.8.1)
Requires-Dist: nonebot2 (>=2.4.2)
